vat_utils/__init__.py
vat_utils/command.py
vat_utils/config.py
vat_utils/misc.py
vat_utils-0.3.1.dist-info/LICENSE.txt
vat_utils-0.3.1.dist-info/METADATA
vat_utils-0.3.1.dist-info/WHEEL
vat_utils-0.3.1.dist-info/RECORD
