Metadata-Version: 2.1
Name: vat-utils
Version: 0.3.1
Summary: 
Author: VAT Dev
Author-email: vatdev@invalid.in
Requires-Python: >=3.6,<4.0
Classifier: Programming Language :: Python :: 3
Classifier: Programming Language :: Python :: 3.6
Classifier: Programming Language :: Python :: 3.7
Classifier: Programming Language :: Python :: 3.8
Classifier: Programming Language :: Python :: 3.9
Classifier: Programming Language :: Python :: 3.10
Classifier: Programming Language :: Python :: 3.11
Requires-Dist: boto3
Requires-Dist: jsonpointer (>=2.0,<3.0)
